pyhiir/__init__.py
pyhiir/allpass.py
pyhiir/hiir.dll
pyhiir/hiir.py
pyhiir-1.0.0.dist-info/LICENSE
pyhiir-1.0.0.dist-info/METADATA
pyhiir-1.0.0.dist-info/WHEEL
pyhiir-1.0.0.dist-info/top_level.txt
pyhiir-1.0.0.dist-info/RECORD
