Metadata-Version: 2.1
Name: pyhiir
Version: 1.0.0
Summary: Python wrapper for HIIR library
Home-page: https://github.com/asanza/pyhiir
Author: Diego Asanza
Author-email: diego.asanza@gmail.com
License-File: LICENSE
Requires-Dist: numpy >=1.19.2
Requires-Dist: scipy >=1.6.3
